plateflo/__init__.py
plateflo/fetbox.py
plateflo/scheduler.py
plateflo/serial_io.py
plateflo/ismatec/__init__.py
plateflo/ismatec/ismatec_dig.py
plateflo/ismatec/ismatec_icc.py
plateflo/ismatec/ismatec_scanner.py
plateflo-0.3.4.dist-info/LICENSE
plateflo-0.3.4.dist-info/METADATA
plateflo-0.3.4.dist-info/WHEEL
plateflo-0.3.4.dist-info/top_level.txt
plateflo-0.3.4.dist-info/RECORD
