Metadata-Version: 2.1
Name: plateflo
Version: 0.3.4
Summary: PlateFlo perfusion system tools.
Home-page: https://github.com/robertpazdzior/plateflo-pypi
Author: Robert Pazdzior
Author-email: rpazdzior@protonmail.com
Classifier: Programming Language :: Python :: 3
Classifier: License :: OSI Approved :: GNU General Public License v3 or later (GPLv3+)
Classifier: Operating System :: OS Independent
Classifier: Development Status :: 3 - Alpha
Requires-Python: >=3.7
License-File: LICENSE
Requires-Dist: pyserial (>=3.5)
